fakedadosbr/__init__.py
fakedadosbr-0.0.2.dist-info/LICENSE.txt
fakedadosbr-0.0.2.dist-info/METADATA
fakedadosbr-0.0.2.dist-info/WHEEL
fakedadosbr-0.0.2.dist-info/top_level.txt
fakedadosbr-0.0.2.dist-info/RECORD
