Metadata-Version: 2.1
Name: fakedadosbr
Version: 0.0.2
Summary: Generic generator fake data for application and api development.
Home-page: https://github.com/juliansantosinfo/fakedadosbr
Author: Julian de Almeida Santos
Author-email: julian.santos.info@gmail.com
License: MIT
Project-URL: Source, https://github.com/juliansantosinfo/fakedadosbr
Keywords: fakedadosbr,fake,cidadao,br
Platform: UNKNOWN
Classifier: Development Status :: 5 - Production/Stable
Classifier: Environment :: Console
Classifier: Environment :: MacOS X
Classifier: Environment :: Web Environment
Classifier: Environment :: X11 Applications
Classifier: Intended Audience :: Developers
Classifier: License :: OSI Approved :: MIT License
Classifier: Operating System :: OS Independent
Classifier: Programming Language :: Python
Classifier: Programming Language :: Python :: 3
Classifier: Programming Language :: Python :: 3 :: Only
Classifier: Programming Language :: Python :: 3.8
Classifier: Programming Language :: Python :: 3.9
Classifier: Topic :: Database
Classifier: Topic :: Internet
Classifier: Topic :: Software Development
Requires-Python: >=3.8
Requires-Dist: requests
Requires-Dist: beautifulsoup4
